sans_webapp/__init__.py
sans_webapp/__main__.py
sans_webapp/app.py
sans_webapp/openai_client.py
sans_webapp/sans_analysis_utils.py
sans_webapp/sans_types.py
sans_webapp/ui_constants.py
sans_webapp/components/__init__.py
sans_webapp/components/data_preview.py
sans_webapp/components/fit_results.py
sans_webapp/components/parameters.py
sans_webapp/components/sidebar.py
sans_webapp/data/simulated_sans_data.csv
sans_webapp/services/__init__.py
sans_webapp/services/ai_chat.py
sans_webapp/services/session_state.py
sans_webapp-0.0.2.dist-info/licenses/LICENSE
sans_webapp-0.0.2.dist-info/METADATA
sans_webapp-0.0.2.dist-info/WHEEL
sans_webapp-0.0.2.dist-info/entry_points.txt
sans_webapp-0.0.2.dist-info/top_level.txt
sans_webapp-0.0.2.dist-info/RECORD
