Metadata-Version: 2.4
Name: sans-webapp
Version: 0.0.2
Summary: A webapp for SANS data fitting using SANS-fitter module.
Author: SANS-webapp contributors
License: BSD-3-Clause
Requires-Python: >=3.10
License-File: LICENSE
Requires-Dist: numpy>=1.20
Requires-Dist: matplotlib>=3.5
Requires-Dist: scipy>=1.7
Requires-Dist: sasmodels>=1.0
Requires-Dist: sasdata>=0.8
Requires-Dist: bumps>=0.9
Requires-Dist: streamlit>=1.28.0
Requires-Dist: plotly>=5.17.0
Requires-Dist: pandas>=2.0.0
Requires-Dist: openai>=1.0.0
Requires-Dist: sans-fitter>=0.0.2
Provides-Extra: dev
Requires-Dist: pytest>=7.0; extra == "dev"
Requires-Dist: pytest-cov>=4.0; extra == "dev"
Provides-Extra: docs
Requires-Dist: mkdocs>=1.5; extra == "docs"
Requires-Dist: mkdocs-material>=9.5; extra == "docs"
Requires-Dist: mkdocstrings[python]>=0.25; extra == "docs"
Dynamic: license-file
